comanage_api/__init__.py
comanage_api/_coorgidentitylinks.py
comanage_api/_copeople.py
comanage_api/_copersonroles.py
comanage_api/_cous.py
comanage_api/_emailaddresses.py
comanage_api/_identifiers.py
comanage_api/_names.py
comanage_api/_orgidentities.py
comanage_api/_sshkeys.py
fabric_comanage_api-0.1.5.dist-info/LICENSE
fabric_comanage_api-0.1.5.dist-info/METADATA
fabric_comanage_api-0.1.5.dist-info/WHEEL
fabric_comanage_api-0.1.5.dist-info/top_level.txt
fabric_comanage_api-0.1.5.dist-info/RECORD
