Metadata-Version: 2.1
Name: fabric-comanage-api
Version: 0.1.5
Summary: Fabric COmanage API
Home-page: https://github.com/fabric-testbed/python-comanage-api
Author: Michael J. Stealey
Author-email: michael.j.stealey@gmail.com
License: MIT
Platform: UNKNOWN
Classifier: Programming Language :: Python :: 3
Classifier: License :: OSI Approved :: MIT License
Classifier: Operating System :: OS Independent
Requires-Python: >=3.6
License-File: LICENSE
Requires-Dist: requests
Requires-Dist: requests-mock
